sphinxcontrib/remoteliteralinclude.py
sphinxcontrib_remoteliteralinclude-0.0.2.dist-info/METADATA
sphinxcontrib_remoteliteralinclude-0.0.2.dist-info/WHEEL
sphinxcontrib_remoteliteralinclude-0.0.2.dist-info/license.txt
sphinxcontrib_remoteliteralinclude-0.0.2.dist-info/top_level.txt
sphinxcontrib_remoteliteralinclude-0.0.2.dist-info/RECORD
