Metadata-Version: 2.1
Name: sphinxcontrib-remoteliteralinclude
Version: 0.0.2
Summary: Extending literalinclude to include remote URLs
Home-page: https://github.com/daltz333/sphinxcontrib-remoteliteralinclude
Author: Eli Barnett, Dalton Smith
Author-email: daltzsmith@gmail.com
License: UNKNOWN
Platform: UNKNOWN
Classifier: Programming Language :: Python :: 3
Classifier: License :: OSI Approved :: MIT License
Classifier: Operating System :: OS Independent
Requires-Python: >=3.4
